priestley_taylor/__init__.py
priestley_taylor/priestley_taylor.py
priestley_taylor/version.py
priestley_taylor-1.1.3.dist-info/licenses/LICENSE
priestley_taylor-1.1.3.dist-info/METADATA
priestley_taylor-1.1.3.dist-info/WHEEL
priestley_taylor-1.1.3.dist-info/top_level.txt
priestley_taylor-1.1.3.dist-info/RECORD
