Metadata-Version: 2.4
Name: priestley-taylor
Version: 1.1.3
Summary: Priestley-Taylor Evapotranspiration Utilities in Python
Author-email: "Gregory H. Halverson" <gregory.h.halverson@jpl.nasa.gov>
Project-URL: Homepage, https://github.com/JPL-Evapotranspiration-Algorithms/priestley-taylor
Classifier: Programming Language :: Python :: 3
Classifier: Operating System :: OS Independent
Requires-Python: >=3.10
License-File: LICENSE
Requires-Dist: check_distribution
Requires-Dist: GEOS5FP
Requires-Dist: numpy
Requires-Dist: rasters
Requires-Dist: SEBAL-soil-heat-flux
Requires-Dist: verma-net-radiation
Provides-Extra: dev
Requires-Dist: build; extra == "dev"
Requires-Dist: pytest>=6.0; extra == "dev"
Requires-Dist: pytest-cov; extra == "dev"
Requires-Dist: jupyter; extra == "dev"
Requires-Dist: pytest; extra == "dev"
Requires-Dist: twine; extra == "dev"
Dynamic: license-file
